president/__main__.py
president/bus.py
president/command.py
president/define.py
president/error.py
president/event.py
president/json.py
president/locks.py
president/object.py
president/parser.py
president/persist.py
president/reactor.py
president/repeater.py
president/run.py
president/thread.py
president/utils.py
president/modules/__init__.py
president/modules/cmd.py
president/modules/dbg.py
president/modules/err.py
president/modules/flt.py
president/modules/irc.py
president/modules/log.py
president/modules/mdl.py
president/modules/mod.py
president/modules/req.py
president/modules/rss.py
president/modules/shp.py
president/modules/sts.py
president/modules/tdo.py
president/modules/thr.py
president/modules/udp.py
president/modules/wsd.py
president-111.data/data/share/doc/president/20140730_011.jpg
president-111.data/data/share/doc/president/20151028_009.jpg
president-111.data/data/share/doc/president/20151029_004.jpg
president-111.data/data/share/doc/president/69389.jpg
president-111.data/data/share/doc/president/BIJWERKING
president-111.data/data/share/doc/president/CONTACT
president-111.data/data/share/doc/president/DOPAMINE
president-111.data/data/share/doc/president/MADS
president-111.data/data/share/doc/president/ONTWENNING
president-111.data/data/share/doc/president/VERGIFTIGING
president-111.data/data/share/doc/president/Wetboek-van-Strafrecht.txt
president-111.data/data/share/doc/president/WvGGZ.rst
president-111.data/data/share/doc/president/WvGGZ.txt
president-111.data/data/share/doc/president/aangifte.rst
president-111.data/data/share/doc/president/aantallen.rst
president-111.data/data/share/doc/president/about.rst
president-111.data/data/share/doc/president/absoluut.rst
president-111.data/data/share/doc/president/absoluut2.jpg
president-111.data/data/share/doc/president/aes.ico
president-111.data/data/share/doc/president/aesculaap.ico
president-111.data/data/share/doc/president/bart.jpg
president-111.data/data/share/doc/president/bart2.jpg
president-111.dist-info/METADATA
president-111.dist-info/WHEEL
president-111.dist-info/entry_points.txt
president-111.dist-info/top_level.txt
president-111.dist-info/zip-safe
president-111.dist-info/RECORD
